pyfixedwidths/__init__.py
pyfixedwidths-0.1.0.dist-info/LICENSE
pyfixedwidths-0.1.0.dist-info/WHEEL
pyfixedwidths-0.1.0.dist-info/METADATA
pyfixedwidths-0.1.0.dist-info/RECORD
