Metadata-Version: 2.1
Name: pyfixedwidths
Version: 0.1.0
Summary: Easy way converting from text, list, or dict to text or list with fixed widths.
Home-page: https://github.com/fkshom
License: MIT
Author: Shoma FUKUDA
Author-email: fkshom+pypi@gmail.com
Requires-Python: >=3.6,<4.0
Classifier: Development Status :: 3 - Alpha
Classifier: Environment :: Console
Classifier: Intended Audience :: Developers
Classifier: License :: OSI Approved :: MIT License
Classifier: Programming Language :: Python :: 3
Classifier: Programming Language :: Python :: 3.6
Classifier: Programming Language :: Python :: 3.7
Classifier: Programming Language :: Python :: 3.8
Classifier: Programming Language :: Python :: 3.9
Classifier: Topic :: Utilities
Project-URL: Documentation, https://github.com/fkshom/pyfixedwidths/wiki
Project-URL: Repository, https://github.com/fkshom/pyfixedwidths
